ezmem/Memory_main.py
ezmem/Prompt.py
ezmem/__init__.py
ezmem/deepseek.py
ezmem-0.2.1.dist-info/LICENSE
ezmem-0.2.1.dist-info/METADATA
ezmem-0.2.1.dist-info/WHEEL
ezmem-0.2.1.dist-info/top_level.txt
ezmem-0.2.1.dist-info/RECORD
