Metadata-Version: 2.2
Name: ezmem
Version: 0.2.1
Summary: A simple AI local memory logic implementation
Author-email: Maple_127667 <1276679255@qq.com>
License: MIT License
Requires-Python: >=3.8
License-File: LICENSE
Requires-Dist: openai
